adafruit_tmp006.py
adafruit_circuitpython_tmp006-2.1.23.dist-info/licenses/LICENSE
adafruit_circuitpython_tmp006-2.1.23.dist-info/METADATA
adafruit_circuitpython_tmp006-2.1.23.dist-info/WHEEL
adafruit_circuitpython_tmp006-2.1.23.dist-info/top_level.txt
adafruit_circuitpython_tmp006-2.1.23.dist-info/RECORD
