Metadata-Version: 2.4
Name: adafruit-circuitpython-tmp006
Version: 2.1.23
Summary: CircuitPython library for TMP006 contactless IR thermometer.
Author-email: Adafruit Industries <circuitpython@adafruit.com>
License: MIT
Project-URL: Homepage, https://github.com/adafruit/Adafruit_CircuitPython_TMP006
Keywords: adafruit,contactless,ir,thermometer,temperature,tmp006,hardware,micropython,circuitpython
Classifier: Intended Audience :: Developers
Classifier: Topic :: Software Development :: Libraries
Classifier: Topic :: Software Development :: Embedded Systems
Classifier: Topic :: System :: Hardware
Classifier: License :: OSI Approved :: MIT License
Classifier: Programming Language :: Python :: 3
License-File: LICENSE
Requires-Dist: Adafruit-Blinka
Requires-Dist: adafruit-circuitpython-busdevice
Provides-Extra: optional
Dynamic: license-file
